{
  "tasks": [
    {
      "id": 1,
      "title": "Task 1",
      "randomNote": "Note 1",
      "dueDate": "2021-01-01",
      "postContent": "Post 1",
      "categories": ["Category 1", "Category 2"],
      "isCompleted": false
    },
    {
      "id": 2,
      "title": "Task 2",
      "randomNote": "Note 2",
      "dueDate": "2021-01-01",
      "postContent": "Post 2",
      "categories": ["Category 2", "Category 4"],
      "isCompleted": false
    },
    {
      "id": 3,
      "title": "Task 3",
      "randomNote": "Note 3",
      "dueDate": "2021-01-01",
      "postContent": "Post 3",
      "categories": ["Category 3", "Category 4"],
      "isCompleted": false
    }
  ]
}
